<?xml version="1.0" encoding="UTF-8"?>
<!DOCTYPE hibernate-mapping PUBLIC
    "-//Hibernate/Hibernate Mapping DTD 3.0//EN" 
    "http://hibernate.sourceforge.net/hibernate-mapping-3.0.dtd">

<hibernate-mapping>
    <class name="org.wikicrimes.model.UsuarioRedeSocial" table="TB_URS_USUARIO_REDE_SOCIAL" lazy="true">
        <id name="idUsuarioRedeSocial" column="URS_IDUSUARIO_REDE_SOCIAL" unsaved-value="null">
            <generator class="increment"/>
        </id>
        <property name="idUsuarioDentroRedeSocial" column="URS_ID_USUARIO_DENTRO_REDE_SOCIAL" type="java.lang.String"/>
        <many-to-one name="redeSocial" column="URS_ID_REDE_SOCIAL" class="org.wikicrimes.model.RedeSocial"/>
        <many-to-one name="usuario" column="URS_ID_USUARIO" class="org.wikicrimes.model.Usuario"/>
        <property name="visualizarCrimes" column="URS_VISUALIZAR_CRIMES" type="java.lang.Boolean"/>
        <property name="dataHoraRegistro" column="URS_DATA_HORA_REGISTRO" type="java.util.Date"/>
        <property name="cidade" column="URS_CIDADE" type="java.lang.String"/>
        <property name="pais" column="URS_PAIS" type="java.lang.String"/>
    </class>
</hibernate-mapping>
